unipruner/.ipynb_checkpoints/__init__-checkpoint.py
unipruner/.ipynb_checkpoints/unipruner-checkpoint.py
unipruner/__init__.py
unipruner/unipruner.py
unipruner-0.3.1.dist-info/LICENSE.txt
unipruner-0.3.1.dist-info/METADATA
unipruner-0.3.1.dist-info/WHEEL
unipruner-0.3.1.dist-info/entry_points.txt
unipruner-0.3.1.dist-info/RECORD
