Metadata-Version: 2.1
Name: unipruner
Version: 0.3.1
Summary: 
License: GNU General Public License v3.0
Author: Gioele Lazzari
Requires-Python: >=3.9
Classifier: License :: Other/Proprietary License
Classifier: Programming Language :: Python :: 3
Classifier: Programming Language :: Python :: 3.9
Classifier: Programming Language :: Python :: 3.10
Classifier: Programming Language :: Python :: 3.11
Classifier: Programming Language :: Python :: 3.12
Requires-Dist: biopython (>=1.80)
Requires-Dist: cobra (>=0.29)
Requires-Dist: gempipe (>=1.37.4)
Requires-Dist: openpyxl (>=3.1.0)
Requires-Dist: pandas (>=2.0.0)
